nekhebet_store/__init__.py
nekhebet_store/hybrid_repository.py
nekhebet_store/lmdb_repository.py
nekhebet_store/pg_repository.py
nekhebet_store-4.0.0.dist-info/METADATA
nekhebet_store-4.0.0.dist-info/WHEEL
nekhebet_store-4.0.0.dist-info/top_level.txt
nekhebet_store-4.0.0.dist-info/RECORD
