Metadata-Version: 2.4
Name: nekhebet-store
Version: 4.0.0
Summary: Nekhebet storage adapters (PostgreSQL, LMDB, hybrid)
Requires-Python: >=3.10
Requires-Dist: nekhebet-core>=4.0.0
Requires-Dist: psycopg2-binary>=2.9
Requires-Dist: lmdb>=1.4.1
